hmku/__init__.py
hmku/demo.py
hmku-1.0.2.dist-info/METADATA
hmku-1.0.2.dist-info/WHEEL
hmku-1.0.2.dist-info/top_level.txt
hmku-1.0.2.dist-info/RECORD
