Metadata-Version: 2.1
Name: hmku
Version: 1.0.2
Summary: 下载韩漫库主页漫画
Author: Yuki
Author-email: 3026408975@qq.com
Classifier: Programming Language :: Python :: 3
Classifier: License :: OSI Approved :: MIT License
Classifier: Operating System :: OS Independent
Requires-Dist: lxml (==4.9.2)
Requires-Dist: requests (==2.28.2)
Requires-Dist: zhconv (==1.4.3)
